simple_ollama_rag/__init__.py
simple_ollama_rag/inference_tools.py
simple_ollama_rag/tools.py
simple_ollama_rag/vectordb_tools.py
simple_ollama_rag-0.1.2.dist-info/METADATA
simple_ollama_rag-0.1.2.dist-info/WHEEL
simple_ollama_rag-0.1.2.dist-info/top_level.txt
simple_ollama_rag-0.1.2.dist-info/RECORD
